{
    "sessionId": "9f8a43361761443db4d27915fd9cec0e",
    "startedAtUtc": "2026-05-20T02:51:43.3045260Z",
    "endedAtUtc": "2026-05-20T02:52:31.9933370Z",
    "endReason": "death",
    "durationSeconds": 48.68904113769531,
    "shotsFired": 0,
    "shotsHit": 4,
    "headHits": 0,
    "reloadsAuto": 0,
    "reloadsManual": 0,
    "damageDealt": 140.0,
    "damageTaken": 109.37503051757813,
    "damageBlockedByArmor": 0.0,
    "enemiesKilled": 2,
    "deaths": 1,
    "pickupsArmor": 0,
    "pickupsMedkit": 0,
    "pickupsMagazines": 0,
    "medkitHealed": 0.0,
    "armorGained": 0.0,
    "ammoGained": 0,
    "accuracy": 0.0,
    "killsPerMinute": 2.464620351791382,
    "damageTakenPerMinute": 134.78395080566407,
    "skillScore": 14.413745880126954
}